README.md
setup.py
nlp_eval/__init__.py
nlp_eval.egg-info/PKG-INFO
nlp_eval.egg-info/SOURCES.txt
nlp_eval.egg-info/dependency_links.txt
nlp_eval.egg-info/top_level.txt