Metadata-Version: 2.1
Name: nlp-eval
Version: 0.1.0
Summary: NLP Evaluation Tool
Home-page: https://github.com/StephenMal/nlp_eval
Author: Stephen Maldonado
Author-email: nlp_eval@stephenmal.com
License: UNKNOWN
Platform: UNKNOWN
Classifier: Development Status :: 1 - Planning
Classifier: Programming Language :: Python :: 3 :: Only
Classifier: Topic :: Utilities
